wcraas_common/__init__.py
wcraas_common/config.py
wcraas_common/decorator.py
wcraas_common/wcraas_common.py
wcraas_common-0.1.7.dist-info/AUTHORS.rst
wcraas_common-0.1.7.dist-info/LICENSE
wcraas_common-0.1.7.dist-info/METADATA
wcraas_common-0.1.7.dist-info/WHEEL
wcraas_common-0.1.7.dist-info/top_level.txt
wcraas_common-0.1.7.dist-info/RECORD
