Metadata-Version: 2.1
Name: wcraas-common
Version: 0.1.7
Summary: WCraaS Storage Service
Home-page: https://github.com/WCraaS/wcraas_common
Author: Kolokotronis Panagiotis
Author-email: panagiks@gmail.com
License: MIT license
Keywords: wcraas_common
Platform: UNKNOWN
Classifier: Development Status :: 2 - Pre-Alpha
Classifier: Intended Audience :: Developers
Classifier: License :: OSI Approved :: MIT License
Classifier: Natural Language :: English
Classifier: Programming Language :: Python :: 3
Classifier: Programming Language :: Python :: 3.6
Classifier: Programming Language :: Python :: 3.7
Requires-Python: >=3.6
Requires-Dist: aio-pika
Requires-Dist: environs
Requires-Dist: yarl (>=1.3.0)
